fontlib/__init__.py
fontlib/__pkginfo__.py
fontlib/api.py
fontlib/cli.py
fontlib/config.py
fontlib/css.py
fontlib/font.py
fontlib/fontstack.py
fontlib/googlefont.py
fontlib/log.py
fontlib/mime.py
fontlib/sphinx.py
fontlib/urlcache.py
fontlib-20190831.1.dist-info/METADATA
fontlib-20190831.1.dist-info/WHEEL
fontlib-20190831.1.dist-info/entry_points.txt
fontlib-20190831.1.dist-info/top_level.txt
fontlib-20190831.1.dist-info/RECORD
