Metadata-Version: 2.1
Name: fontlib
Version: 20190831.1
Summary: Pluginable font library
Home-page: https://github.com/return42/fontlib
Author: Markus Heiser
Author-email: markus.heiser@darmarIT.de
Maintainer: Markus Heiser
Maintainer-email: markus.heiser@darmarIT.de
License: GPLv2
Project-URL: Documentation, http://return42.github.io/fontlib
Project-URL: Code, https://github.com/return42/fontlib
Project-URL: Issue tracker, https://github.com/return42/fontlib/issues
Keywords: fonts TTF OTF WOFF WOFF2
Platform: UNKNOWN
Classifier: Development Status :: 5 - Production/Stable
Classifier: Intended Audience :: Developers
Classifier: License :: OSI Approved :: GNU General Public License v2 (GPLv2)
Classifier: Operating System :: OS Independent
Classifier: Programming Language :: Python
Classifier: Programming Language :: Python :: 3
Classifier: Programming Language :: Python :: Implementation :: CPython
Classifier: Programming Language :: Python :: Implementation :: PyPy
Classifier: Topic :: Software Development :: Libraries :: Application Frameworks
Classifier: Topic :: Software Development :: Libraries :: Python Modules
Requires-Dist: fspath
Requires-Dist: tinycss2
Requires-Dist: requests
Provides-Extra: dev
Requires-Dist: jedi ; extra == 'dev'
Requires-Dist: Sphinx ; extra == 'dev'
Requires-Dist: sphinx-rtd-theme ; extra == 'dev'
Requires-Dist: sphinx-autobuild ; extra == 'dev'
Requires-Dist: sphinxcontrib-programoutput ; extra == 'dev'
Requires-Dist: pip ; extra == 'dev'
Requires-Dist: twine ; extra == 'dev'
Provides-Extra: test
Requires-Dist: pylint ; extra == 'test'
